dynamic_file/__init__.py
dynamic_file/admin.py
dynamic_file/apps.py
dynamic_file/config.py
dynamic_file/storage.py
dynamic_file/migrations/0001_initial.py
dynamic_file/migrations/0002_alter_dynamicfile_file.py
dynamic_file/migrations/0003_alter_dynamicfile_uploaded_by.py
dynamic_file/migrations/0004_dynamicfile_created_at_dynamicfile_updated_at.py
dynamic_file/migrations/__init__.py
dynamic_file/models/__init__.py
dynamic_file/models/base.py
dynamic_file/models/file.py
dynamic_file/serializers/__init__.py
dynamic_file/serializers/fields.py
dynamic_file/views/__init__.py
dynamic_file/views/serve_file.py
django_dynamic_file-0.6.1.dist-info/LICENSE
django_dynamic_file-0.6.1.dist-info/METADATA
django_dynamic_file-0.6.1.dist-info/WHEEL
django_dynamic_file-0.6.1.dist-info/top_level.txt
django_dynamic_file-0.6.1.dist-info/RECORD
