Metadata-Version: 2.2
Name: django-dynamic-file
Version: 0.6.1
Summary: A flexible approach to handling and serving files with django
Author-email: Philipp Hafner <philipp@hafner.xyz>
License: MIT License
Project-URL: Homepage, https://github.com/Hafnernuss/django-dynamic-file
Keywords: django,file
Classifier: License :: OSI Approved :: MIT License
Classifier: Programming Language :: Python
Classifier: Programming Language :: Python :: 3
Requires-Python: >=3.9
License-File: LICENSE
Requires-Dist: djangorestframework>=3.12.4
Requires-Dist: Django>=3.0
Provides-Extra: dev
Requires-Dist: pytest; extra == "dev"
